freemoneycow/__init__.py
freemoneycow/banque.py
freemoneycow-0.2.0.dist-info/WHEEL
freemoneycow-0.2.0.dist-info/entry_points.txt
freemoneycow-0.2.0.dist-info/METADATA
freemoneycow-0.2.0.dist-info/RECORD
